{
    "lesson": "Умумий қоидалар",
    "data": [
        {
            "id": 933,
            "bilet_id": 47,
            "question_id": 5,
            "name": null,
            "question": {
                "oz": "Agar avtomobilning o'ng g'ildiraklari nam qoplamali yo'l yoqasiga chiqib qolsa, tavsiya etiladi:",
                "uz": "Агар автомобилнинг ўнг ғилдираклари нам қопламали йўл ёқасига чиқиб қолса, тавсия этилади:",
                "ru": "В случае, когда правые колёса автомобиля наезжают на неукреплённую влажную обочину, рекомендуется:"
            },
            "photo": null,
            "answers": {
                "status": 3,
                "answer_id": 5,
                "answer": {
                    "oz": [
                        "Avtomobilni tormozlash va to'liq to'xtatish",
                        "Avtomobilni tormozlab, yo'lning harakat qismiga ohista ravon burish",
                        "Avtomobilni tormozlamasdan yo'lning harakat qismiga oxista ravon burish"
                    ],
                    "uz": [
                        "Автомобилни тормозлаш ва тўлиқ тўхтатиш",
                        "Автомобилни тормозлаб, йўлнинг ҳаракат қисмига оҳиста равон буриш",
                        "Автомобилни тормозламасдан йўлнинг ҳаракат қисмига охиста равон буриш"
                    ],
                    "ru": [
                        "Затормозить и полностью остановиться",
                        "Затормозить и плавно направить автомобиль на проезжую часть",
                        "Не прибегая к торможению, плавно направить автомобиль на проезжую часть"
                    ]
                }
            }
        },
        {
            "id": 559,
            "bilet_id": 28,
            "question_id": 9,
            "name": null,
            "question": {
                "oz": "Egiluvchan ulagichda shatakka olganda transport vositalari orasidagi masofa qanday bo'lishi kerak?",
                "uz": "Эгилувчан улагичда шатакка олганда транспорт воситалари орасидаги масофа қандай бўлиши керак?",
                "ru": "Какое расстояние между транспортными средствами должна обеспечить гибкая сцепка?"
            },
            "photo": null,
            "answers": {
                "status": 4,
                "answer_id": 9,
                "answer": {
                    "oz": [
                        "1-3 m",
                        "2-4 m",
                        "3-6 m",
                        "4-6 m",
                        "4-8 m"
                    ],
                    "uz": [
                        "1-3 м",
                        "2-4 м",
                        "3-6 м",
                        "4-6 м",
                        "4-8 м"
                    ],
                    "ru": [
                        "1-3 м",
                        "2-4 м",
                        "3-6 м",
                        "4-6 м",
                        "4-8 м"
                    ]
                }
            }
        },
        {
            "id": 31,
            "bilet_id": 2,
            "question_id": 11,
            "name": null,
            "question": {
                "oz": "Mazkur yo'l belgisi nimani bildiradi?",
                "uz": "Мазкур йўл белгиси нимани билдиради?",
                "ru": "Этот дорожный знак обозначает:"
            },
            "photo": "2.11.webp",
            "answers": {
                "status": 2,
                "answer_id": 11,
                "answer": {
                    "oz": [
                        "Yo'lning trotuar yoki piyodalar yo'lkasi bo'lgan qismini",
                        "Yo'lning piyodalar o'tish joyi bo'lgan qismini"
                    ],
                    "uz": [
                        "Йўлнинг тротуар ёки пиёдалар йўлкаси бўлган қисмини",
                        "Йўлнинг пиёдалар ўтиш жойи бўлган қисмини"
                    ],
                    "ru": [
                        "Участок дороги, на котором имеется тротуар или пешеходная дорожка",
                        "Участок дороги, на котором имеется пешеходный переход"
                    ]
                }
            }
        },
        {
            "id": 875,
            "bilet_id": 44,
            "question_id": 9,
            "name": null,
            "question": {
                "oz": "Tezlik ortishi bilan haydovchining ko'rish maydoni qanday o'zgaradi?",
                "uz": "Тезлик ортиши билан ҳайдовчининг кўриш майдони қандай ўзгаради?",
                "ru": "Как изменяется поле зрение водителя с увелечением скорости движения?"
            },
            "photo": null,
            "answers": {
                "status": 3,
                "answer_id": 9,
                "answer": {
                    "oz": [
                        "Kengayadi",
                        "O'zgarmaydi",
                        "Torayadi"
                    ],
                    "uz": [
                        "Кенгаяди",
                        "Ўзгармайди",
                        "Тораяди"
                    ],
                    "ru": [
                        "Расширяется",
                        "Не изменяется",
                        "Сужается"
                    ]
                }
            }
        },
        {
            "id": 920,
            "bilet_id": 46,
            "question_id": 12,
            "name": null,
            "question": {
                "oz": "Miltillovchi sariq ishorali svetofor:",
                "uz": "Милтилловчи сариқ ишорали светофор:",
                "ru": "Мигающий жёлтый сигнал светафора:"
            },
            "photo": null,
            "answers": {
                "status": 1,
                "answer_id": 12,
                "answer": {
                    "oz": [
                        "Tartibga solinmagan chorraha yoki piyodalar o'tish joyi borligidan xabardor qiladi",
                        "Tartibga solingan chorraha borligidan xabardor qiladi",
                        "Svetofor chirog'i almashuvidan xabardor qiladi"
                    ],
                    "uz": [
                        "Тартибга солинмаган чорраҳа ёки пиёдалар ўтиш жойи борлигидан хабардор қилади",
                        "Тартибга солинган чорраҳа борлигидан хабардор қилади",
                        "Светофор чироғи алмашувидан хабардор қилади"
                    ],
                    "ru": [
                        "Информирует о наличии нерегулируемого перекрестка или пешеходного перехода",
                        "Информирует о наличии нерегулируемого перекрестка",
                        "Сигнал светафора уведомляет вас об изменении цвета"
                    ]
                }
            }
        },
        {
            "id": 986,
            "bilet_id": 49,
            "question_id": 9,
            "name": null,
            "question": {
                "oz": "Siz to'g'ri yo'lda harakatlanayotib to'satdan yo'lning qisman katta bo'lmagan sirpanchiq qismiga duch keldingiz. Bunda qanday ehtiyot choralarini ko'rasiz?",
                "uz": "Сиз тўғри йўлда ҳаракатланаётиб тўсатдан йўлнинг қисман катта бўлмаган сирпанчиқ қисмига дуч келдингиз. Бунда қандай эҳтиёт чораларини кўрасиз?",
                "ru": "Двигаясь в прямом направлении, Вы внезапно попали на небольшой участок скользкой дороги. Что следует предпринять?"
            },
            "photo": null,
            "answers": {
                "status": 3,
                "answer_id": 9,
                "answer": {
                    "oz": [
                        "Avtomobilni ohista to'xtatish",
                        "Rulni  burib sirpanchiqdan chiqib ketish ",
                        "Harakat yo'nalishini va tezlikni o'zgartirmasdan ehtiyotkorlik bilan o'tib ketish  "
                    ],
                    "uz": [
                        "Автомобилни оҳиста тўхтатиш",
                        "Рулни  буриб сирпанчиқдан чиқиб кетиш ",
                        "Ҳаракат йўналишини ва тезликни ўзгартирмасдан эҳтиёткорлик билан ўтиб кетиш  "
                    ],
                    "ru": [
                        "Плавно затормозить",
                        "Повернуть руль, чтобы съехать с этого участка дороги",
                        "Проехать не меняя траектории и скорости движения"
                    ]
                }
            }
        },
        {
            "id": 72,
            "bilet_id": 4,
            "question_id": 3,
            "name": null,
            "question": {
                "oz": "Ushbu yo'l belgisi qo'shimcha axborot belgisi bilan nimani bildiradi?",
                "uz": "Ушбу йўл белгиси қўшимча ахборот белгиси билан нимани билдиради?",
                "ru": "Этот дорожный знак обозначает:"
            },
            "photo": "4.3.webp",
            "answers": {
                "status": 3,
                "answer_id": 3,
                "answer": {
                    "oz": [
                        "Ruxsat etilgan to'la vazni 3,5 t dan ortiq transport vositalarining to'xtab turish joyi ko'rsatkich qatnov qismining chetida baland to'siq, toshi borligini bildiradi",
                        "Transport vositalarining to'xtab turish joyiga avtomobilni ko'rsatilgan usulda qo'yish taqiqlanadi",
                        "Engil avtomobillar va motosikllarni to'xtab turishga qo'yish joyi va usuli"
                    ],
                    "uz": [
                        "Рухсат этилган тўла вазни 3,5 т дан ортиқ транспорт воситаларининг тўхтаб туриш жойи кўрсаткич қатнов қисмининг четида баланд тўсиқ, тоши борлигини билдиради",
                        "Транспорт воситаларининг тўхтаб туриш жойига автомобилни кўрсатилган усулда қўйиш тақиқланади",
                        "Енгил автомобиллар ва мотоциклларни тўхтаб туришга қўйиш жойи ва усули"
                    ],
                    "ru": [
                        "Место стоянки транспортных средств с разрешенной максимальной массой более 3,5 т. Табличка указывает, что у края проезжей части высокий бордюрный камень",
                        "Место стоянки транспортных средств; способ постановки автомобиля; указанный на табличке запрещается",
                        "Место и способ постановки легковых автомобилей и мотоциклов на стоянке"
                    ]
                }
            }
        },
        {
            "id": 233,
            "bilet_id": 12,
            "question_id": 3,
            "name": null,
            "question": {
                "oz": "Rasmda ko'rsatilgan holatda yo'lovchilarni tushirish uchun to'xtashga ruxsat beriladimi?",
                "uz": "Расмда кўрсатилган ҳолатда йўловчиларни тушириш учун тўхташга рухсат бериладими?",
                "ru": "Разрешается ли остановка для высадки пассажира в ситуации; показанной на рисунке?"
            },
            "photo": "12.3.webp",
            "answers": {
                "status": 1,
                "answer_id": 3,
                "answer": {
                    "oz": [
                        "Ruxsat etiladi",
                        "Taqiqlanadi"
                    ],
                    "uz": [
                        "Рухсат этилади",
                        "Таъқиқланади"
                    ],
                    "ru": [
                        "Разрешается",
                        "Запрещается"
                    ]
                }
            }
        },
        {
            "id": 741,
            "bilet_id": 37,
            "question_id": 11,
            "name": null,
            "question": {
                "oz": "108 km/s tezlikda harakatlanayotgan transport vositasi 1 sekundda qancha masofani bosib o'tadi?",
                "uz": "108 км/с тезликда ҳаракатланаётган транспорт воситаси 1 секундда қанча масофани босиб ўтади?",
                "ru": "Какое расстояние проедет транспортное средство за одну секунду при скорости движения 108 км/ч?"
            },
            "photo": null,
            "answers": {
                "status": 3,
                "answer_id": 11,
                "answer": {
                    "oz": [
                        "15 m",
                        "25 m",
                        "30 m"
                    ],
                    "uz": [
                        "15 м",
                        "25 м",
                        "30 м"
                    ],
                    "ru": [
                        "15 м",
                        "25 м",
                        "30 м"
                    ]
                }
            }
        },
        {
            "id": 6,
            "bilet_id": 1,
            "question_id": 6,
            "name": null,
            "question": {
                "oz": "Qaysi transport vositasining haydovchisi chorrahadan birinchi bo'lib o'tadi?",
                "uz": "Қайси транспорт воситасининг ҳайдовчиси чорраҳадан биринчи бўлиб ўтади?",
                "ru": "Водители каких транспортных средств проедут перекресток первыми?"
            },
            "photo": "1.6.webp",
            "answers": {
                "status": 1,
                "answer_id": 6,
                "answer": {
                    "oz": [
                        "Avtomobil va avtobus haydovchisi",
                        "Tramvay haydovchisi"
                    ],
                    "uz": [
                        "Автомобил ва автобус ҳайдовчиси",
                        "Трамвай ҳайдовчиси"
                    ],
                    "ru": [
                        "Водители автомобиля и автобуса",
                        "Водитель трамвая"
                    ]
                }
            }
        },
        {
            "id": 819,
            "bilet_id": 41,
            "question_id": 12,
            "name": null,
            "question": {
                "oz": "Ko'rsatilgan yo'l belgilaridan qaysi biri taqiqlovchi belgilar ilgari kiritgan barcha cheklovlarni bekor qiladi?",
                "uz": "Кўрсатилган йўл белгиларидан қайси бири таъқиқловчи белгилар илгари киритган барча чекловларни бекор қилади?",
                "ru": "Какой из перечисленных дорожных знаков отменяет все ограничения, ранее введенные запрещающими знаками?"
            },
            "photo": "41.12.webp",
            "answers": {
                "status": 1,
                "answer_id": 12,
                "answer": {
                    "oz": [
                        "V",
                        "A va B",
                        "V va G",
                        "Barchasi"
                    ],
                    "uz": [
                        "В",
                        "А ва Б",
                        "В ва Г",
                        "Барчаси"
                    ],
                    "ru": [
                        "В",
                        "А и Б",
                        "В и Г",
                        "Все"
                    ]
                }
            }
        },
        {
            "id": 373,
            "bilet_id": 19,
            "question_id": 3,
            "name": null,
            "question": {
                "oz": "Bu yotiq chiziq nimani bildiradi?",
                "uz": "Бу ётиқ чизиқ нимани билдиради?",
                "ru": "Эта горизонтальная дорожная разметка обозначает:"
            },
            "photo": "19.3.webp",
            "answers": {
                "status": 2,
                "answer_id": 3,
                "answer": {
                    "oz": [
                        "Mazkur yo'nalishda harakatlanish bo'lagi soni kamaya borib, qatnov qismining torayishini",
                        "Kesib o'tiladigan yo'l bo'ylab harakatlanayotgan transport vositasiga yo'l berar ekan, haydovchi zarur holda qaerda to'xtashi kerak bo'lgan joyni",
                        "To'xtash taqiqlangan joyga yaqinlashilganini"
                    ],
                    "uz": [
                        "Мазкур йўналишда ҳаракатланиш бўлаги сони камая бориб, қатнов қисмининг торайишини",
                        "Кесиб ўтиладиган йўл бўйлаб ҳаракатланаётган транспорт воситасига йўл берар экан, ҳайдовчи зарур ҳолда қаерда тўхташи керак бўлган жойни",
                        "Тўхташ тақиқланган жойга яқинлашилганини"
                    ],
                    "ru": [
                        "Сужение проезжей части, где уменьшается количество полос движения в данном направлении",
                        "Место, где водитель должен при необходимости остановиться, уступая дорогу транспортным средствам движущимся по пересекаемой дороге",
                        "Приближение к месту где запрещена остановка"
                    ]
                }
            }
        },
        {
            "id": 248,
            "bilet_id": 12,
            "question_id": 18,
            "name": null,
            "question": {
                "oz": "Belgilangan yo'nalishdagi transport vositalari yoki taksilarning to'xtab turish maydonchalaridan ular bo'lmagan hollarda, (yo'nalishli transport voistalari harakatiga xalaqit bermasa) belgi ko'rsatkichlaridan qanday masofada to'xtash va to'xtab turish taqiqlanadi?",
                "uz": "Белгиланган йўналишдаги транспорт воситалари ёки таксиларнинг тўхтаб туриш майдончаларидан улар бўлмаган ҳолларда, (йўналишли транспорт воисталари ҳаракатига халақит бермаса) белги кўрсаткичларидан қандай масофада тўхташ ва тўхтаб туриш тақиқланади?",
                "ru": "Ближе какого расстояния запрещается остановка и стоянка от остановочных площадок, а при их отсутствии, от указателя остановки маршрутных транспортных средств или такси, если это создает помехи их движению?"
            },
            "photo": null,
            "answers": {
                "status": 3,
                "answer_id": 18,
                "answer": {
                    "oz": [
                        "5 m",
                        "10 m",
                        "15 m",
                        "20 m",
                        "25 m"
                    ],
                    "uz": [
                        "5 m",
                        "10 m",
                        "15 m",
                        "20 m",
                        "25 m"
                    ],
                    "ru": [
                        "5 m",
                        "10 m",
                        "15 m",
                        "20 m",
                        "25 m"
                    ]
                }
            }
        },
        {
            "id": 867,
            "bilet_id": 44,
            "question_id": 1,
            "name": null,
            "question": {
                "oz": "Yo'l harakati qoidalariga ko'ra yo'l belgilari nechta guruhga bo'linadi",
                "uz": "Йўл ҳаракати қоидаларига кўра йўл белгилари нечта гуруҳга бўлинади",
                "ru": "По правилам дорожного движения дорожные знаки делятся на сколько групп?"
            },
            "photo": null,
            "answers": {
                "status": 3,
                "answer_id": 1,
                "answer": {
                    "oz": [
                        "5",
                        "6",
                        "7"
                    ],
                    "uz": [
                        "5",
                        "6",
                        "7"
                    ],
                    "ru": [
                        "5",
                        "6",
                        "7"
                    ]
                }
            }
        },
        {
            "id": 825,
            "bilet_id": 41,
            "question_id": 18,
            "name": null,
            "question": {
                "oz": "G'ildiraklarni yo'l bilan ilashishi yo'qolganda (kuchli yomg'ir, sel yoki suv toshgan yo'l qismlari) haydovchi:",
                "uz": "Ғилдиракларни йўл билан илашиши йўқолганда (кучли ёмғир, сел ёки сув тошган йўл қисмлари) ҳайдовчи:",
                "ru": "При потере сцепления колёс с дорогой (сильный дождь или затопление участка дороги) водитель:"
            },
            "photo": null,
            "answers": {
                "status": 3,
                "answer_id": 18,
                "answer": {
                    "oz": [
                        "Tezlikni oshirish lozim",
                        "Tormoz tepkisini keskin bosish bilan tezlikni kamaytirish lozim",
                        "Dvigatel bilan tormozlash orqali tezlikni kamaytirishi lozim"
                    ],
                    "uz": [
                        "Тезликни ошириш лозим",
                        "Тормоз тепкисини кескин босиш билан тезликни камайтириш лозим",
                        "Двигател билан тормозлаш орқали тезликни камайтириши лозим"
                    ],
                    "ru": [
                        "Должен увеличить скорость.",
                        "Он должен снизить скорость, резко нажав на педаль тормоза.",
                        "Необходимо снизить скорость и применить торможение двигателем."
                    ]
                }
            }
        },
        {
            "id": 31,
            "bilet_id": 2,
            "question_id": 11,
            "name": null,
            "question": {
                "oz": "Mazkur yo'l belgisi nimani bildiradi?",
                "uz": "Мазкур йўл белгиси нимани билдиради?",
                "ru": "Этот дорожный знак обозначает:"
            },
            "photo": "2.11.webp",
            "answers": {
                "status": 2,
                "answer_id": 11,
                "answer": {
                    "oz": [
                        "Yo'lning trotuar yoki piyodalar yo'lkasi bo'lgan qismini",
                        "Yo'lning piyodalar o'tish joyi bo'lgan qismini"
                    ],
                    "uz": [
                        "Йўлнинг тротуар ёки пиёдалар йўлкаси бўлган қисмини",
                        "Йўлнинг пиёдалар ўтиш жойи бўлган қисмини"
                    ],
                    "ru": [
                        "Участок дороги, на котором имеется тротуар или пешеходная дорожка",
                        "Участок дороги, на котором имеется пешеходный переход"
                    ]
                }
            }
        },
        {
            "id": 440,
            "bilet_id": 22,
            "question_id": 10,
            "name": null,
            "question": {
                "oz": "Ishlamayotgan boshqaruv ruli bilan to'xtab turish yoki tamirlash joyiga borishga ruxsat etiladimi?",
                "uz": "Ишламаётган бошқарув рули билан тўхтаб туриш ёки таъмирлаш жойига боришга рухсат этиладими?",
                "ru": "Разрешается ли следовать к месту стоянки или ремонта с недействующим рулевым управлением?"
            },
            "photo": null,
            "answers": {
                "status": 3,
                "answer_id": 10,
                "answer": {
                    "oz": [
                        "Qattiq ulagichda shatakka olinganda ruxsat etiladi",
                        "Harakat havfsizligini taminlovchi tezlikda ruxsat etiladi",
                        "Taqiqlanadi"
                    ],
                    "uz": [
                        "Қаттиқ улагичда шатакка олинганда рухсат этилади",
                        "Ҳаракат ҳавфсизлигини таъминловчи тезликда рухсат этилади",
                        "Тақиқланади"
                    ],
                    "ru": [
                        "Разрешается при буксировке на жесткой сцепке",
                        "Разрешается со скоростью обеспечивающей безопасность движения",
                        "Запрещается"
                    ]
                }
            }
        },
        {
            "id": 258,
            "bilet_id": 13,
            "question_id": 8,
            "name": null,
            "question": {
                "oz": "Ko'rsatilgan vaziyatda engil avtomobil haydovchisiga quvib o'tishga ruxsat etiladimi?",
                "uz": "Кўрсатилган вазиятда енгил автомобиль ҳайдовчисига қувиб ўтишга рухсат этиладими?",
                "ru": "Разрешен ли водителю легкового автомобиля обгон в показанной ситуации?"
            },
            "photo": "13.8.webp",
            "answers": {
                "status": 3,
                "answer_id": 8,
                "answer": {
                    "oz": [
                        "Ruxsat etilgan",
                        "Ruxsat etilgan, agar motosiklchining tezligi 40 km/soatdan kam bo'lsa",
                        "Taqiqlangan"
                    ],
                    "uz": [
                        "Рухсат этилган",
                        "Рухсат этилган, агар мотоциклчининг тезлиги 40 км/соатдан кам бўлса",
                        "Таъқиқланган"
                    ],
                    "ru": [
                        "Разрешен",
                        "Разрешен, если скорость мотоциклиста менее 40 км/ч",
                        "Запрещен"
                    ]
                }
            }
        },
        {
            "id": 816,
            "bilet_id": 41,
            "question_id": 9,
            "name": null,
            "question": {
                "oz": "Quyidagi belgilardan qaysi biri haydovchini boshqa xavf-xatarlar to'g'risida ogohlantiradi?",
                "uz": "Қуйидаги белгилардан қайси бири ҳайдовчини бошқа хавф-хатарлар тўғрисида огоҳлантиради?",
                "ru": "Какой из указанных знаков предупреждает водителя о других опасностях?"
            },
            "photo": "41.9.webp",
            "answers": {
                "status": 3,
                "answer_id": 9,
                "answer": {
                    "oz": [
                        "A",
                        "B",
                        "V"
                    ],
                    "uz": [
                        "А",
                        "Б",
                        "В"
                    ],
                    "ru": [
                        "А",
                        "Б",
                        "В"
                    ]
                }
            }
        },
        {
            "id": 929,
            "bilet_id": 47,
            "question_id": 1,
            "name": null,
            "question": {
                "oz": "Yo'nalishli bo'lmagan transport vositalari “A” xarfi bilan belgilangan o'ng bo'lakda qaysi holatlarda harakatlanishlari mumkin?",
                "uz": "Йўналишли бўлмаган транспорт воситалари “А” харфи билан белгиланган ўнг бўлакда қайси ҳолатларда ҳаракатланишлари мумкин?",
                "ru": "В каких случаях немаршрутные транспортные средства могут двигаться по правой полосе, обозначенной буквой «А»?"
            },
            "photo": "47.1.webp",
            "answers": {
                "status": 3,
                "answer_id": 1,
                "answer": {
                    "oz": [
                        "O'nga burilishda",
                        "Yo'lovchilarni chiqarish va tushirishda",
                        "Yuqoridagi barcha xolatlarda agarda yo'nalishli transport vositalariga xalaqit bermasa"
                    ],
                    "uz": [
                        "Ўнга бурилишда",
                        "Йўловчиларни чиқариш ва туширишда",
                        "Юқоридаги барча холатларда агарда йўналишли транспорт воситаларига халақит бермаса"
                    ],
                    "ru": [
                        "При повороте направо",
                        "При посадке и высадке пассажиров",
                        "Во всех вышеперечисленных случаях, если  не мешает движению маршрутных транспортных средств."
                    ]
                }
            }
        }
    ]
}