{
    "lesson": "Умумий қоидалар",
    "data": [
        {
            "id": 303,
            "bilet_id": 15,
            "question_id": 13,
            "name": null,
            "question": {
                "oz": "Bu yo'l chizig'i nimani bildiradi?",
                "uz": "Бу йўл чизиғи нимани билдиради?",
                "ru": "Эта дорожная разметка обозначает?"
            },
            "photo": "15.13.webp",
            "answers": {
                "status": 2,
                "answer_id": 13,
                "answer": {
                    "oz": [
                        "Yakka 40 km/s dan kam tezlik bilan harakat qiluvchi ikki g'ildirakli motosikllar, velosipedchilardan tashqari barcha transport vositalarini quvib o'tishni taqiqlovchi hududga",
                        "Qatnov qismining torayishiga yoki qarama-qarshi yo'nalishdan kelayotgan transport oqimini ajratuvchi 1,1 yoki 1,11 chizig'iga yaqinlashayotganini",
                        "Faqat belgilangan yo'nalishdagi transport vositalari harakati uchun mo'ljallangan qatnov qismi bo'lagiga"
                    ],
                    "uz": [
                        "Якка 40 км/с дан кам тезлик билан ҳаракат қилувчи икки ғилдиракли мотоцикллар, велосипедчилардан ташқари барча транспорт воситаларини қувиб ўтишни тақиқловчи ҳудудга",
                        "Қатнов қисмининг торайишига ёки қарама-қарши йўналишдан келаётган транспорт оқимини ажратувчи 1,1 ёки 1,11 чизиғига яқинлашаётганини",
                        "Фақат белгиланган йўналишдаги транспорт воситалари ҳаракати учун мўлжалланган қатнов қисми бўлагига"
                    ],
                    "ru": [
                        "Зону, в которой запрещается обгонять все транспортные средства, кроме одиночных, движущихся со скоростью менее 30 км/ч двухколесных мотоциклов, велосипедистов",
                        ". Приближение к сужению проезжей части или к линии разметки; разделяющей транспортные потоки противоположных направлений",
                        "Приближение к полосе проезжей части; предназначенной для движения только маршрутных транспортных средств"
                    ]
                }
            }
        },
        {
            "id": 844,
            "bilet_id": 42,
            "question_id": 18,
            "name": null,
            "question": {
                "oz": "Avtomobillarning bir qator bo'lib harakatlanishi uchun etarlicha keng bo'lgan, yo'l chiziqlari bilan belgilangan yoki belgilanmagan yo'l qatnov qismining har qanday bo'ylama bo'lagi nima deb ataladi?",
                "uz": "Автомобилларнинг бир қатор бўлиб ҳаракатланиши учун етарлича кенг бўлган, йўл чизиқлари билан белгиланган ёки белгиланмаган йўл қатнов қисмининг ҳар қандай бўйлама бўлаги нима деб аталади?",
                "ru": "Как называется любая из продольных полос проезжей части, обозначенная или не обозначенная дорожной разметкой и имеющая ширину, достаточную для движения в один раз?"
            },
            "photo": null,
            "answers": {
                "status": 2,
                "answer_id": 18,
                "answer": {
                    "oz": [
                        "Qatnov qismi",
                        "Harakatlanish tasmasi",
                        "Yo'l yoqasi",
                        "Yondosh hudud"
                    ],
                    "uz": [
                        "Қатнов қисми",
                        "Ҳаракатланиш тасмаси",
                        "Йўл ёқаси",
                        "Ёндош ҳудуд"
                    ],
                    "ru": [
                        "Проезжная часть",
                        "Полоса движения",
                        "Обочина дороги",
                        "Прилегающая территория"
                    ]
                }
            }
        },
        {
            "id": 189,
            "bilet_id": 9,
            "question_id": 19,
            "name": null,
            "question": {
                "oz": "Qattiq yoki egiluvchan ulagich yordamida shatakka olinganda, yuk avtomobilining yukxonasida odamlarni tashishga ruxsat beriladimi?",
                "uz": "Қаттиқ ёки эгилувчан улагич ёрдамида шатакка олинганда, юк автомобилининг юкхонасида одамларни ташишга рухсат бериладими?",
                "ru": "Разрешается ли перевозка людей в кузове грузового автомобиля при буксировке на жесткой или гибкой сцепке?"
            },
            "photo": null,
            "answers": {
                "status": 3,
                "answer_id": 19,
                "answer": {
                    "oz": [
                        "Shatakka olgan va shatakka olingan avtomobillarning yukxonasida ruxsat beriladi",
                        "Faqat shatakka olingan avtomobil yukxonasida ruxsat beriladi",
                        "Faqat shatakka olgan avtomobil yukxonasida ruxsat beriladi"
                    ],
                    "uz": [
                        "Шатакка олган ва шатакка олинган автомобилларнинг юкхонасида рухсат берилади",
                        "Фақат шатакка олинган автомобиль юкхонасида рухсат берилади",
                        "Фақат шатакка олган автомобиль юкхонасида рухсат берилади"
                    ],
                    "ru": [
                        "Разрешается в багажнике буксирующего и буксируемого автомобилей",
                        "Разрешено только в багажнике автомобиля; который был отбуксирован",
                        "Разрешается только в багажнике буксирующего автомобиля"
                    ]
                }
            }
        },
        {
            "id": 912,
            "bilet_id": 46,
            "question_id": 4,
            "name": null,
            "question": {
                "oz": "Bu joyda yo'lovchilarni chiqarish yoki tushirish maqsadida to'xtash mumkinmi?",
                "uz": "Бу жойда йўловчиларни чиқариш ёки тушириш мақсадида тўхташ мумкинми?",
                "ru": "Можно ли остановиться в этом месте для посадки или высадки пассажира?"
            },
            "photo": "46.4.webp",
            "answers": {
                "status": 1,
                "answer_id": 4,
                "answer": {
                    "oz": [
                        "Ha",
                        "Yo'q"
                    ],
                    "uz": [
                        "Ҳа",
                        "Йўқ"
                    ],
                    "ru": [
                        "Да",
                        "Нет"
                    ]
                }
            }
        },
        {
            "id": 123,
            "bilet_id": 6,
            "question_id": 13,
            "name": null,
            "question": {
                "oz": "Haydovchiga transport vositalarining to'xtab turish joylari chegarasini bildiradigan uzluksiz chiziqni kesib o'tishga ruxsat etiladimi?",
                "uz": "Ҳайдовчига транспорт воситаларининг тўхтаб туриш жойлари чегарасини билдирадиган узлуксиз чизиқни кесиб ўтишга рухсат этиладими?",
                "ru": "Разрешается ли водителю пересекать сплошную линию разметки; обозначающую границы стояночных мест транспортных средств?"
            },
            "photo": "6.13.webp",
            "answers": {
                "status": 2,
                "answer_id": 13,
                "answer": {
                    "oz": [
                        "To'xtash uchun ruxsat etiladi",
                        "Taqiqlanadi",
                        "Kirish va chiqish uchun ruxsat etiladi",
                        "Hamma hollarda ruxsat etiladi, agar to'xtab turish joyida boshqa transport vositalari yo'q bo'lsa"
                    ],
                    "uz": [
                        "Тўхташ учун рухсат этилади",
                        "Тақиқланади",
                        "Кириш ва чиқиш учун рухсат этилади",
                        "Ҳамма ҳолларда рухсат этилади, агар тўхтаб туриш жойида бошқа транспорт воситалари йўқ бўлса"
                    ],
                    "ru": [
                        "Разрешается для остановки",
                        "Запрещается",
                        "Разрешается для въезда и выезда",
                        "Разрешается в любом случае, если на стоянке нет других транспортных средств"
                    ]
                }
            }
        },
        {
            "id": 280,
            "bilet_id": 14,
            "question_id": 10,
            "name": null,
            "question": {
                "oz": "Bolalarni tashkiliy tashishda qanday talablar qo'yiladi?",
                "uz": "Болаларни ташкилий ташишда қандай талаблар қўйилади?",
                "ru": "Каковы требования для организованной перевозки группа детей?"
            },
            "photo": null,
            "answers": {
                "status": 4,
                "answer_id": 10,
                "answer": {
                    "oz": [
                        "Bolalar guruhini tashkiliy tashishda transport vositasida katta yoshli kuzatib boruvchi bo'lishi shart",
                        "Bolalar guruhini tashkiliy tashish uchun mo'ljallangan transport vositasining old va orqa tomoniga «Болалар гуруҳини ташиш» taniqlik belgisi o'rnatilishi kerak",
                        "Belgilangan yo'nalishdagi transport vositalariga daxli bo'lmagan avtobuslarda sakkiz va undan ortiq bolalarning tashkiliy tashilishi",
                        "Barcha sanab o'tilgan talablar"
                    ],
                    "uz": [
                        "Болалар гуруҳини ташкилий ташишда транспорт воситасида катта ёшли кузатиб борувчи бўлиши шарт",
                        "Болалар гуруҳини ташкилий ташиш учун мўлжалланган транспорт воситасининг олд ва орқа томонига «Болалар гуруҳини ташиш» таниқлик белгиси ўрнатилиши керак",
                        "Белгиланган йўналишдаги транспорт воситаларига дахли бўлмаган автобусларда саккиз ва ундан ортиқ болаларнинг ташкилий ташилиши",
                        "Барча санаб ўтилган талаблар"
                    ],
                    "ru": [
                        "При организации группы детей в автомобиле должен присутствовать наблюдатель",
                        "На передней и задней части транспортного средства; должна быть знак «Перевозка детей»",
                        "Организованная перевозка восьми и более детей на автобусах, не вписывающихся в установленный маршрут",
                        "Во всех перечисленных случаях"
                    ]
                }
            }
        },
        {
            "id": 156,
            "bilet_id": 8,
            "question_id": 6,
            "name": null,
            "question": {
                "oz": "Haydovchi manyovrni bajarishda burilish ko'rsatkichlari bilan yorug'lik ishorasini har doim berishi kerakmi?",
                "uz": "Ҳайдовчи манёврни бажаришда бурилиш кўрсаткичлари билан ёруғлик ишорасини ҳар доим бериши керакми?",
                "ru": "Всегда ли водитель должен подавать световой сигнал; указателями поворота при выполнении маневра?"
            },
            "photo": null,
            "answers": {
                "status": 2,
                "answer_id": 6,
                "answer": {
                    "oz": [
                        "Har doim berishi kerak",
                        "Kerak emas, agar harakatlanishning boshqa qatnashchilarini chalg'itishi mumkin bo'lsa",
                        "Kerak, zaruriy ehtiyot choralarini ko'rgan holda"
                    ],
                    "uz": [
                        "Ҳар доим бериши керак",
                        "Керак эмас, агар ҳаракатланишнинг бошқа қатнашчиларини чалғитиши мумкин бўлса",
                        "Керак, зарурий эҳтиёт чораларини кўрган ҳолда"
                    ],
                    "ru": [
                        "Должен всегда",
                        "Не должен, если он может ввести в заблуждение других участников движения",
                        "Должен, приняв необходимые меры предосторожности"
                    ]
                }
            }
        },
        {
            "id": 809,
            "bilet_id": 41,
            "question_id": 2,
            "name": null,
            "question": {
                "oz": "Ushbu belgi...",
                "uz": "Ушбу белги...",
                "ru": "Этот знак..."
            },
            "photo": "41.2.webp",
            "answers": {
                "status": 2,
                "answer_id": 2,
                "answer": {
                    "oz": [
                        "Oldinda harakatlanish serqatnovligi haqida ogohlantiradi",
                        "Oldinda transport vositalarning tirbandligi haqida ogohlantiradi",
                        "Oldinda transport vositalari orasida xavfsiz oraliqni taminlash lozimligi haqida ogohlantiradi."
                    ],
                    "uz": [
                        "Олдинда ҳаракатланиш серқатновлиги ҳақида огоҳлантиради",
                        "Олдинда транспорт воситаларнинг тирбандлиги ҳақида огоҳлантиради",
                        "Олдинда транспорт воситалари орасида хавфсиз оралиқни таъминлаш лозимлиги ҳақида огоҳлантиради."
                    ],
                    "ru": [
                        "Предупреждает об интенсивном движении транспортных средств.",
                        "Предупреждает о заторах впереди.",
                        "Предупреждает о необходимости обеспечения безопасной дистанции между впереди идущими автомобилями"
                    ]
                }
            }
        },
        {
            "id": 434,
            "bilet_id": 22,
            "question_id": 4,
            "name": null,
            "question": {
                "oz": "Qaysi transport vositasi haydovchisi yo'l berishi kerak?",
                "uz": "Қайси транспорт воситаси ҳайдовчиси йўл бериши керак?",
                "ru": "Водитель какого транспортного средства должен уступить дорогу?"
            },
            "photo": "22.4.webp",
            "answers": {
                "status": 2,
                "answer_id": 4,
                "answer": {
                    "oz": [
                        "Avtomobil haydovchisi",
                        "Motosikl haydovchisi"
                    ],
                    "uz": [
                        "Автомобил ҳайдовчиси",
                        "Мотоцикл ҳайдовчиси"
                    ],
                    "ru": [
                        "Водитель автомобиля",
                        "Водитель мотоцикла"
                    ]
                }
            }
        },
        {
            "id": 157,
            "bilet_id": 8,
            "question_id": 7,
            "name": null,
            "question": {
                "oz": "Suratlarning qaysi birida quvib o'tish ko'rsatilgan?",
                "uz": "Суратларнинг қайси бирида қувиб ўтиш кўрсатилган?",
                "ru": "На каком из рисунков показан обгон?"
            },
            "photo": "8.7.webp",
            "answers": {
                "status": 1,
                "answer_id": 7,
                "answer": {
                    "oz": [
                        "«А»",
                        "«Б»",
                        "«А» va «Б»"
                    ],
                    "uz": [
                        "«А»",
                        "«Б»",
                        "«А» ва «Б»"
                    ],
                    "ru": [
                        "«А»",
                        "«Б»",
                        "«А» и «Б»"
                    ]
                }
            }
        },
        {
            "id": 359,
            "bilet_id": 18,
            "question_id": 9,
            "name": null,
            "question": {
                "oz": "To'rmoz yo'li deganda nimani tushunasiz?",
                "uz": "Тўрмоз йўли деганда нимани тушунасиз?",
                "ru": "Что называется тормозным путем?"
            },
            "photo": null,
            "answers": {
                "status": 2,
                "answer_id": 9,
                "answer": {
                    "oz": [
                        "Haydovchiga xavf malum bo'lgan vaqtdan boshlab avtomobilning to'liq to'xtagungacha bosib o'tgan masofasi",
                        "Tormoz tepkisini bosilgan vaqtidan boshlab avtomobilning to'liq to'xtagungacha bosib o'tgan yo'li"
                    ],
                    "uz": [
                        "Ҳайдовчига хавф маълум бўлган вақтдан бошлаб автомобилнинг тўлиқ тўхтагунгача босиб ўтган масофаси",
                        "Тормоз тепкисини босилган вақтидан бошлаб автомобилнинг тўлиқ тўхтагунгача босиб ўтган йўли"
                    ],
                    "ru": [
                        "Расстояние; пройденное автомобилем с момента обнаружения водителем опасности до полной остановки",
                        "Расстояние; пройденное автомобилем с момента нажатия на педаль тормоза до полной остановки"
                    ]
                }
            }
        },
        {
            "id": 15,
            "bilet_id": 1,
            "question_id": 15,
            "name": null,
            "question": {
                "oz": "Qaysi transport vositasi haydovchisi to'g'riga harakatlanish huquqiga ega?",
                "uz": "Қайси транспорт воситаси ҳайдовчиси тўғрига ҳаракатланиш ҳуқуқига эга?",
                "ru": "Кто из водителей имеет право двигаться в прямом направлении?"
            },
            "photo": "1.15.webp",
            "answers": {
                "status": 3,
                "answer_id": 15,
                "answer": {
                    "oz": [
                        "Avtobus va motosikl haydovchilari",
                        "Engil va yuk avtomobillari haydovchilari",
                        "Engil avtomobil haydovchisi"
                    ],
                    "uz": [
                        "Автобус ва мотоцикл ҳайдовчилари",
                        "Енгил ва юк автомобиллари ҳайдовчилари",
                        "Енгил автомобил ҳайдовчиси"
                    ],
                    "ru": [
                        "Водители автобуса и мотоцикла",
                        "Водители легкового и грузового автомобилей",
                        "Водитель легкового автомобиля"
                    ]
                }
            }
        },
        {
            "id": 433,
            "bilet_id": 22,
            "question_id": 3,
            "name": null,
            "question": {
                "oz": "Transport vositasining haydovchisi oldida «to'xtash chizig'i» chizilgan va svetoforning yashil yoritkichi yoniq bo'lgan chorrahaga yaqinlashayotib nima qilishi kerak?",
                "uz": "Транспорт воситасининг ҳайдовчиси олдида «тўхташ чизиғи» чизилган ва светофорнинг яшил ёриткичи ёниқ бўлган чорраҳага яқинлашаётиб нима қилиши керак?",
                "ru": "Что обязан выполнить водитель транспортного средства приблизившись к перекрестку перед которым нанесена «cтоп-линия» и включен зеленый сигнал светофора?"
            },
            "photo": null,
            "answers": {
                "status": 2,
                "answer_id": 3,
                "answer": {
                    "oz": [
                        "«Тўхташ чизиғи»da to'xtashi, so'ng esa harakatni qayta tiklashi",
                        "To'xtamasdan chorraha orqali harakatni davom ettirishi"
                    ],
                    "uz": [
                        "«Тўхташ чизиғи»да тўхташи, сўнг эса ҳаракатни қайта тиклаши",
                        "Тўхтамасдан чорраҳа орқали ҳаракатни давом эттириши"
                    ],
                    "ru": [
                        "Остановиться у «cтоп-линий», а затем возобновить движение",
                        "Продолжить движение через перекресток без остановки"
                    ]
                }
            }
        },
        {
            "id": 522,
            "bilet_id": 26,
            "question_id": 12,
            "name": null,
            "question": {
                "oz": "Belgilardan qaysi biri bevosita yo'lning xavfli qismi oldiga o'rnatiladi?",
                "uz": "Белгилардан қайси бири бевосита йўлнинг хавфли қисми олдига ўрнатилади?",
                "ru": "Какой из знаков устанавливается непосредственно перед опасным участком дороги?"
            },
            "photo": "26.12.webp",
            "answers": {
                "status": 5,
                "answer_id": 12,
                "answer": {
                    "oz": [
                        "1",
                        "2",
                        "3",
                        "4",
                        "5"
                    ],
                    "uz": [
                        "1",
                        "2",
                        "3",
                        "4",
                        "5"
                    ],
                    "ru": [
                        "1",
                        "2",
                        "3",
                        "4",
                        "5"
                    ]
                }
            }
        },
        {
            "id": 107,
            "bilet_id": 5,
            "question_id": 17,
            "name": null,
            "question": {
                "oz": "Bu erda quvib o'tishga ruxsat beriladimi?",
                "uz": "Бу ерда қувиб ўтишга рухсат бериладими?",
                "ru": "Разрешается ли обгон в данной ситуации?"
            },
            "photo": "5.17.webp",
            "answers": {
                "status": 2,
                "answer_id": 17,
                "answer": {
                    "oz": [
                        "Ruxsat beriladi",
                        "Taqiqlanadi"
                    ],
                    "uz": [
                        "Рухсат берилади",
                        "Тақиқланади"
                    ],
                    "ru": [
                        "Разрешается",
                        "Запрещается"
                    ]
                }
            }
        },
        {
            "id": 213,
            "bilet_id": 11,
            "question_id": 3,
            "name": null,
            "question": {
                "oz": "Yo'naltirgichlar bilan ko'rsatilgan yo'nalishlarning qaysi biridan harakat qilish mumkin?",
                "uz": "Йўналтиргичлар билан кўрсатилган йўналишларнинг қайси биридан ҳаракат қилиш мумкин?",
                "ru": "По какому пути из числа обозначенных стрелками разрешено движение?"
            },
            "photo": "11.3.webp",
            "answers": {
                "status": 1,
                "answer_id": 3,
                "answer": {
                    "oz": [
                        "Faqat to'g'riga",
                        "Chapga va orqaga",
                        "To'g'riga, chapga va orqaga"
                    ],
                    "uz": [
                        "Фақат тўғрига",
                        "Чапга ва орқага",
                        "Тўғрига, чапга ва орқага"
                    ],
                    "ru": [
                        "Только прямо",
                        "Налево и в обратном направлении",
                        "Прямо, налево и в обратном направлении"
                    ]
                }
            }
        },
        {
            "id": 711,
            "bilet_id": 36,
            "question_id": 1,
            "name": null,
            "question": {
                "oz": "Svetaforning yashil miltillovchi ishorasi nimani bildiradi?",
                "uz": "Светафорнинг яшил милтилловчи ишораси нимани билдиради?",
                "ru": "Что означает мигание зеленого сигнала светофора?"
            },
            "photo": null,
            "answers": {
                "status": 2,
                "answer_id": 1,
                "answer": {
                    "oz": [
                        "Svetafor nosozligini",
                        "Harakatga ruxsat beradi va tez orada taqiqlovchi ishora yonishi to'g'risida axborot beradi",
                        "Harakatni davom ettirishni taqiqlaydi"
                    ],
                    "uz": [
                        "Светафор носозлигини",
                        "Ҳаракатга рухсат беради ва тез орада тақиқловчи ишора ёниши тўғрисида ахборот беради",
                        "Ҳаракатни давом эттиришни тақиқлайди"
                    ],
                    "ru": [
                        "Предупреждает о неисправности светофора",
                        "Разрешает движение и информирует о том, что вскоре будет включен запрещающий сигнал",
                        "Запрещает дальнейшее движение"
                    ]
                }
            }
        },
        {
            "id": 1009,
            "bilet_id": 50,
            "question_id": 19,
            "name": null,
            "question": {
                "oz": "Qaysi belgi tartibga solinmagan piyodalar o'tish joyiga yaqinlashayotganlik haqida ogohlantiradi?",
                "uz": "Қайси белги тартибга солинмаган пиёдалар ўтиш жойига яқинлашаётганлик ҳақида огоҳлантиради?",
                "ru": "Какой знак предупреждает о приближении к нерегулируемому пешеходному переходу?"
            },
            "photo": "50.19.webp",
            "answers": {
                "status": 1,
                "answer_id": 19,
                "answer": {
                    "oz": [
                        "Faqat A",
                        "A va V",
                        "Xammasi"
                    ],
                    "uz": [
                        "Фақат А",
                        "А ва В",
                        "Хаммаси"
                    ],
                    "ru": [
                        "Только А",
                        "А ва В",
                        "Все"
                    ]
                }
            }
        },
        {
            "id": 905,
            "bilet_id": 45,
            "question_id": 19,
            "name": null,
            "question": {
                "oz": "Ushbu belgilardan qaysi biri oldinda yo'l qoplamasi ustida suniy notekslik borligi haqida ogohlantiradi?",
                "uz": "Ушбу белгилардан қайси бири олдинда йўл қопламаси устида сунъий нотекслик борлиги ҳақида огоҳлантиради?",
                "ru": "Какой из этих знаков предупреждает о наличии впереди искусственной неровности дорожного покрытия?"
            },
            "photo": "45.19.webp",
            "answers": {
                "status": 2,
                "answer_id": 19,
                "answer": {
                    "oz": [
                        "A",
                        "V",
                        "S",
                        "A va S"
                    ],
                    "uz": [
                        "А",
                        "В",
                        "С",
                        "А ва С"
                    ],
                    "ru": [
                        "А",
                        "В",
                        "С",
                        "А и С"
                    ]
                }
            }
        },
        {
            "id": 1065,
            "bilet_id": 53,
            "question_id": 13,
            "name": null,
            "question": {
                "oz": "Qaysi rasmda piyoda qoidani buzgan holda yo'lni kesib o'tyabdi?",
                "uz": "Қайси расмда пиёда қоидани бузган ҳолда йўлни кесиб ўтябди?",
                "ru": "На каком снимке пешеход переходил дорогу с нарушением правил?"
            },
            "photo": "53.13.webp",
            "answers": {
                "status": 2,
                "answer_id": 13,
                "answer": {
                    "oz": [
                        "1-2-rasmdagi piyoda",
                        "3-rasmdagi piyoda",
                        "4-rasmdagi piyoda",
                        "Barcha rasmdagi piyoda"
                    ],
                    "uz": [
                        "1-2-расмдаги пиёда",
                        "3-расмдаги пиёда",
                        "4-расмдаги пиёда",
                        "Барча расмдаги пиёда"
                    ],
                    "ru": [
                        "Пиеда 1-2 на рисунке",
                        "Пиеда на рисунке 3",
                        "Пиеда на рисунке 4",
                        "Пиеда на всех картинах"
                    ]
                }
            }
        }
    ]
}